LICENSE
MANIFEST.in
README.md
setup.py
cookiestxt/_MozillaCookieJar.py
cookiestxt/__init__.py
cookiestxt.egg-info/PKG-INFO
cookiestxt.egg-info/SOURCES.txt
cookiestxt.egg-info/dependency_links.txt
cookiestxt.egg-info/top_level.txt